clusterfunc/__init__.py
clusterfunc-0.0.1.dist-info/METADATA
clusterfunc-0.0.1.dist-info/RECORD
clusterfunc-0.0.1.dist-info/WHEEL
clusterfunc-0.0.1.dist-info/top_level.txt
